__builtins__.pyi
_boot.pyi
_onewire.pyi
_thread.pyi
_uasyncio.pyi
apa106.pyi
array.pyi
binascii.pyi
bluetooth.pyi
btree.pyi
cmath.pyi
collections.pyi
cryptolib.pyi
dht.pyi
ds18x20.pyi
errno.pyi
esp.pyi
esp32.pyi
flashbdev.pyi
framebuf.pyi
gc.pyi
hashlib.pyi
heapq.pyi
inisetup.pyi
io.pyi
json.pyi
machine.pyi
math.pyi
micropython.pyi
mip/__init__.pyi
mip.pyi
neopixel.pyi
network.pyi
ntptime.pyi
onewire.pyi
os.pyi
platform.pyi
random.pyi
select.pyi
socket.pyi
ssl.pyi
struct.pyi
sys.pyi
time.pyi
uarray.pyi
uasyncio/__init__.pyi
uasyncio/core.pyi
uasyncio/event.pyi
uasyncio/funcs.pyi
uasyncio/lock.pyi
uasyncio/stream.pyi
uasyncio/task.pyi
ubinascii.pyi
ubluetooth.pyi
ucollections.pyi
ucryptolib.pyi
uctypes.pyi
uerrno.pyi
uhashlib.pyi
uheapq.pyi
uio.pyi
ujson.pyi
umachine.pyi
umqtt/__init__.pyi
umqtt/robust.pyi
umqtt/simple.pyi
uos.pyi
uplatform.pyi
upysh.pyi
urandom.pyi
ure.pyi
urequests.pyi
uselect.pyi
usocket.pyi
ussl.pyi
ustruct.pyi
usys.pyi
utime.pyi
utimeq.pyi
uwebsocket.pyi
uzlib.pyi
webrepl.pyi
webrepl_setup.pyi
websocket.pyi
zlib.pyi
micropython_esp32_generic_s3_stubs-1.20.0.post1.dist-info/LICENSE.md
micropython_esp32_generic_s3_stubs-1.20.0.post1.dist-info/METADATA
micropython_esp32_generic_s3_stubs-1.20.0.post1.dist-info/WHEEL
micropython_esp32_generic_s3_stubs-1.20.0.post1.dist-info/RECORD
